netmath/__init__.py
netmath/version.py
netmath-1.0.2.dist-info/METADATA
netmath-1.0.2.dist-info/WHEEL
netmath-1.0.2.dist-info/top_level.txt
netmath-1.0.2.dist-info/RECORD
